demo/__init__.py
demo/demo.py
demo/demo_unlink.py
demo/simple-demo.py
demo/rpc/__init__.py
demo/rpc/rpc_client_pipe.py
demo/rpc/rpc_server_pipe.py
demo/rpc/utlis.py
demo/socket_logger/__init__.py
demo/socket_logger/custom_events.py
demo/socket_logger/video_stream.py
pipert2/__init__.py
pipert2/contrib/__init__.py
pipert2/contrib/message_handlers/__init__.py
pipert2/contrib/networks/__init__.py
pipert2/contrib/routines/__init__.py
pipert2/core/__init__.py
pipert2/core/base/__init__.py
pipert2/core/base/data_transmitter.py
pipert2/core/base/flow.py
pipert2/core/base/message.py
pipert2/core/base/payload.py
pipert2/core/base/pipe.py
pipert2/core/base/routine.py
pipert2/core/base/wire.py
pipert2/core/base/data/__init__.py
pipert2/core/base/data/data.py
pipert2/core/base/data/frame_data.py
pipert2/core/base/routines/__init__.py
pipert2/core/base/routines/extended_run_factory.py
pipert2/core/base/routines/fps_routine.py
pipert2/core/base/routines/functional_middle_routine.py
pipert2/core/base/synchronise_routines/__init__.py
pipert2/core/base/synchronise_routines/routines_synchroniser.py
pipert2/core/base/synchronise_routines/synchroniser_node.py
pipert2/core/base/transmitters/__init__.py
pipert2/core/base/transmitters/basic_transmitter.py
pipert2/core/base/transmitters/shared_memory_transmitter.py
pipert2/core/base/validators/__init__.py
pipert2/core/base/validators/flow_validator.py
pipert2/core/handlers/__init__.py
pipert2/core/handlers/event_handler.py
pipert2/core/handlers/message_handler.py
pipert2/core/handlers/message_handlers/__init__.py
pipert2/core/handlers/message_handlers/queue_handler.py
pipert2/core/managers/__init__.py
pipert2/core/managers/event_board.py
pipert2/core/managers/network.py
pipert2/core/managers/networks/__init__.py
pipert2/core/managers/networks/queue_network.py
pipert2/core/wrappers/__init__.py
pipert2/core/wrappers/api_wrapper.py
pipert2/core/wrappers/rpc_pipe_wrapper.py
pipert2/core/wrappers/utils.py
pipert2/utils/__init__.py
PipeRT-2.4.0.dist-info/LICENSE
PipeRT-2.4.0.dist-info/METADATA
PipeRT-2.4.0.dist-info/WHEEL
PipeRT-2.4.0.dist-info/top_level.txt
PipeRT-2.4.0.dist-info/RECORD
