Metadata-Version: 2.1
Name: PipeRT
Version: 2.4.0
Summary: Real-time pipeline 4 analytics
Home-page: https://github.com/OperationalBina/PipeRT2
Author: digitalTevel
Author-email: digitalTevel@gmail.com
License: UNKNOWN
Project-URL: Bug Tracker, https://github.com/OperationalBina/PipeRT2/issues
Platform: UNKNOWN
Classifier: Programming Language :: Python :: 3
Classifier: License :: OSI Approved :: MIT License
Classifier: Operating System :: OS Independent
Requires-Python: >=3.6
License-File: LICENSE
Requires-Dist: numpy
Provides-Extra: api
Requires-Dist: flask ; extra == 'api'
Requires-Dist: flask-cors ; extra == 'api'
Provides-Extra: cockpit
Requires-Dist: opencv-python ; extra == 'cockpit'
Requires-Dist: python-socketio ; extra == 'cockpit'
Requires-Dist: websocket-client ; extra == 'cockpit'
Provides-Extra: rpc
Requires-Dist: zerorpc ; extra == 'rpc'
Provides-Extra: shared_memory
Requires-Dist: posix-ipc ; extra == 'shared_memory'
